[
  {
    "entities": [
      [
        0,
        11,
        "PERSON"
      ],
      [
        12,
        28,
        "JOB"
      ],
      [
        29,
        48,
        "ADDRESS"
      ],
      [
        49,
        68,
        "EMAIL"
      ],
      [
        69,
        83,
        "PHONE"
      ],
      [
        98,
        104,
        "SKILL"
      ],
      [
        106,
        122,
        "SKILL"
      ],
      [
        124,
        127,
        "SKILL"
      ],
      [
        129,
        135,
        "SKILL"
      ]
    ]
  },
  {
    "entities": [
      [
        0,
        10,
        "PERSON"
      ],
      [
        11,
        30,
        "JOB"
      ],
      [
        31,
        50,
        "ADDRESS"
      ],
      [
        51,
        71,
        "EMAIL"
      ],
      [
        72,
        86,
        "PHONE"
      ],
      [
        101,
        104,
        "SKILL"
      ],
      [
        106,
        113,
        "SKILL"
      ],
      [
        115,
        134,
        "SKILL"
      ],
      [
        136,
        141,
        "SKILL"
      ]
    ]
  },
  {
    "entities": [
      [
        0,
        10,
        "PERSON"
      ],
      [
        11,
        30,
        "JOB"
      ],
      [
        31,
        53,
        "ADDRESS"
      ],
      [
        54,
        73,
        "EMAIL"
      ],
      [
        74,
        88,
        "PHONE"
      ],
      [
        103,
        109,
        "SKILL"
      ],
      [
        111,
        129,
        "SKILL"
      ],
      [
        131,
        137,
        "SKILL"
      ],
      [
        139,
        155,
        "SKILL"
      ]
    ]
  },
  {
    "entities": [
      [
        0,
        10,
        "PERSON"
      ],
      [
        11,
        27,
        "JOB"
      ],
      [
        28,
        46,
        "ADDRESS"
      ],
      [
        47,
        65,
        "EMAIL"
      ],
      [
        66,
        80,
        "PHONE"
      ],
      [
        95,
        101,
        "SKILL"
      ],
      [
        103,
        118,
        "SKILL"
      ],
      [
        120,
        128,
        "SKILL"
      ],
      [
        130,
        140,
        "SKILL"
      ]
    ]
  },
  {
    "entities": [
      [
        0,
        10,
        "PERSON"
      ],
      [
        11,
        32,
        "JOB"
      ],
      [
        33,
        52,
        "ADDRESS"
      ],
      [
        53,
        73,
        "EMAIL"
      ],
      [
        74,
        88,
        "PHONE"
      ],
      [
        103,
        122,
        "SKILL"
      ],
      [
        124,
        139,
        "SKILL"
      ],
      [
        141,
        147,
        "SKILL"
      ],
      [
        149,
        165,
        "SKILL"
      ]
    ]
  },
  {
    "entities": [
      [
        0,
        11,
        "PERSON"
      ],
      [
        12,
        21,
        "JOB"
      ],
      [
        22,
        44,
        "ADDRESS"
      ],
      [
        45,
        69,
        "EMAIL"
      ],
      [
        70,
        84,
        "PHONE"
      ],
      [
        99,
        102,
        "SKILL"
      ],
      [
        104,
        110,
        "SKILL"
      ],
      [
        112,
        115,
        "SKILL"
      ],
      [
        117,
        139,
        "SKILL"
      ]
    ]
  },
  {
    "entities": [
      [
        0,
        13,
        "PERSON"
      ],
      [
        14,
        36,
        "JOB"
      ],
      [
        37,
        60,
        "ADDRESS"
      ],
      [
        61,
        80,
        "EMAIL"
      ],
      [
        81,
        95,
        "PHONE"
      ],
      [
        110,
        115,
        "SKILL"
      ],
      [
        117,
        133,
        "SKILL"
      ],
      [
        135,
        153,
        "SKILL"
      ],
      [
        155,
        177,
        "SKILL"
      ]
    ]
  },
  {
    "entities": [
      [
        0,
        12,
        "PERSON"
      ],
      [
        13,
        25,
        "JOB"
      ],
      [
        26,
        48,
        "ADDRESS"
      ],
      [
        49,
        73,
        "EMAIL"
      ],
      [
        74,
        88,
        "PHONE"
      ],
      [
        103,
        121,
        "SKILL"
      ],
      [
        123,
        131,
        "SKILL"
      ],
      [
        133,
        152,
        "SKILL"
      ],
      [
        154,
        171,
        "SKILL"
      ]
    ]
  },
  {
    "entities": [
      [
        0,
        12,
        "PERSON"
      ],
      [
        13,
        32,
        "JOB"
      ],
      [
        33,
        55,
        "ADDRESS"
      ],
      [
        56,
        75,
        "EMAIL"
      ],
      [
        76,
        90,
        "PHONE"
      ],
      [
        105,
        121,
        "SKILL"
      ],
      [
        123,
        129,
        "SKILL"
      ],
      [
        131,
        147,
        "SKILL"
      ],
      [
        149,
        157,
        "SKILL"
      ]
    ]
  },
  {
    "entities": [
      [
        0,
        12,
        "PERSON"
      ],
      [
        13,
        29,
        "JOB"
      ],
      [
        30,
        49,
        "ADDRESS"
      ],
      [
        50,
        69,
        "EMAIL"
      ],
      [
        70,
        84,
        "PHONE"
      ],
      [
        99,
        104,
        "SKILL"
      ],
      [
        106,
        111,
        "SKILL"
      ],
      [
        113,
        123,
        "SKILL"
      ],
      [
        125,
        144,
        "SKILL"
      ]
    ]
  },
  {
    "entities": [
      [
        0,
        11,
        "PERSON"
      ],
      [
        12,
        31,
        "JOB"
      ],
      [
        32,
        54,
        "ADDRESS"
      ],
      [
        55,
        74,
        "EMAIL"
      ],
      [
        75,
        89,
        "PHONE"
      ],
      [
        104,
        111,
        "SKILL"
      ],
      [
        113,
        130,
        "SKILL"
      ],
      [
        132,
        150,
        "SKILL"
      ],
      [
        152,
        155,
        "SKILL"
      ]
    ]
  },
  {
    "entities": [
      [
        0,
        12,
        "PERSON"
      ],
      [
        13,
        29,
        "JOB"
      ],
      [
        30,
        48,
        "ADDRESS"
      ],
      [
        49,
        73,
        "EMAIL"
      ],
      [
        74,
        88,
        "PHONE"
      ],
      [
        103,
        106,
        "SKILL"
      ],
      [
        108,
        113,
        "SKILL"
      ],
      [
        115,
        137,
        "SKILL"
      ],
      [
        139,
        157,
        "SKILL"
      ]
    ]
  },
  {
    "entities": [
      [
        0,
        10,
        "PERSON"
      ],
      [
        11,
        30,
        "JOB"
      ],
      [
        31,
        53,
        "ADDRESS"
      ],
      [
        54,
        73,
        "EMAIL"
      ],
      [
        74,
        88,
        "PHONE"
      ],
      [
        103,
        109,
        "SKILL"
      ],
      [
        111,
        126,
        "SKILL"
      ],
      [
        128,
        134,
        "SKILL"
      ],
      [
        136,
        143,
        "SKILL"
      ]
    ]
  },
  {
    "entities": [
      [
        0,
        11,
        "PERSON"
      ],
      [
        12,
        21,
        "JOB"
      ],
      [
        22,
        40,
        "ADDRESS"
      ],
      [
        41,
        60,
        "EMAIL"
      ],
      [
        61,
        75,
        "PHONE"
      ],
      [
        90,
        109,
        "SKILL"
      ],
      [
        111,
        127,
        "SKILL"
      ],
      [
        129,
        135,
        "SKILL"
      ],
      [
        137,
        140,
        "SKILL"
      ]
    ]
  },
  {
    "entities": [
      [
        0,
        10,
        "PERSON"
      ],
      [
        11,
        23,
        "JOB"
      ],
      [
        24,
        47,
        "ADDRESS"
      ],
      [
        48,
        72,
        "EMAIL"
      ],
      [
        73,
        87,
        "PHONE"
      ],
      [
        102,
        107,
        "SKILL"
      ],
      [
        109,
        125,
        "SKILL"
      ],
      [
        127,
        137,
        "SKILL"
      ],
      [
        139,
        142,
        "SKILL"
      ]
    ]
  },
  {
    "entities": [
      [
        0,
        10,
        "PERSON"
      ],
      [
        11,
        23,
        "JOB"
      ],
      [
        24,
        47,
        "ADDRESS"
      ],
      [
        48,
        67,
        "EMAIL"
      ],
      [
        68,
        82,
        "PHONE"
      ],
      [
        97,
        103,
        "SKILL"
      ],
      [
        105,
        112,
        "SKILL"
      ],
      [
        114,
        130,
        "SKILL"
      ],
      [
        132,
        138,
        "SKILL"
      ]
    ]
  },
  {
    "entities": [
      [
        0,
        10,
        "PERSON"
      ],
      [
        11,
        27,
        "JOB"
      ],
      [
        28,
        47,
        "ADDRESS"
      ],
      [
        48,
        67,
        "EMAIL"
      ],
      [
        68,
        82,
        "PHONE"
      ],
      [
        97,
        115,
        "SKILL"
      ],
      [
        117,
        122,
        "SKILL"
      ],
      [
        124,
        127,
        "SKILL"
      ],
      [
        129,
        145,
        "SKILL"
      ]
    ]
  },
  {
    "entities": [
      [
        0,
        10,
        "PERSON"
      ],
      [
        11,
        31,
        "JOB"
      ],
      [
        32,
        54,
        "ADDRESS"
      ],
      [
        55,
        73,
        "EMAIL"
      ],
      [
        74,
        88,
        "PHONE"
      ],
      [
        103,
        109,
        "SKILL"
      ],
      [
        111,
        114,
        "SKILL"
      ],
      [
        116,
        131,
        "SKILL"
      ],
      [
        133,
        136,
        "SKILL"
      ]
    ]
  },
  {
    "entities": [
      [
        0,
        13,
        "PERSON"
      ],
      [
        14,
        35,
        "JOB"
      ],
      [
        36,
        55,
        "ADDRESS"
      ],
      [
        56,
        74,
        "EMAIL"
      ],
      [
        75,
        89,
        "PHONE"
      ],
      [
        104,
        120,
        "SKILL"
      ],
      [
        122,
        128,
        "SKILL"
      ],
      [
        130,
        135,
        "SKILL"
      ],
      [
        137,
        142,
        "SKILL"
      ]
    ]
  },
  {
    "entities": [
      [
        0,
        13,
        "PERSON"
      ],
      [
        14,
        30,
        "JOB"
      ],
      [
        31,
        54,
        "ADDRESS"
      ],
      [
        55,
        74,
        "EMAIL"
      ],
      [
        75,
        89,
        "PHONE"
      ],
      [
        104,
        120,
        "SKILL"
      ],
      [
        122,
        128,
        "SKILL"
      ],
      [
        130,
        135,
        "SKILL"
      ],
      [
        137,
        143,
        "SKILL"
      ]
    ]
  },
  {
    "entities": [
      [
        0,
        12,
        "PERSON"
      ],
      [
        13,
        22,
        "JOB"
      ],
      [
        23,
        41,
        "ADDRESS"
      ],
      [
        42,
        62,
        "EMAIL"
      ],
      [
        63,
        77,
        "PHONE"
      ],
      [
        92,
        97,
        "SKILL"
      ],
      [
        99,
        109,
        "SKILL"
      ],
      [
        111,
        118,
        "SKILL"
      ],
      [
        120,
        126,
        "SKILL"
      ]
    ]
  },
  {
    "entities": [
      [
        0,
        11,
        "PERSON"
      ],
      [
        12,
        28,
        "JOB"
      ],
      [
        29,
        52,
        "ADDRESS"
      ],
      [
        53,
        71,
        "EMAIL"
      ],
      [
        72,
        86,
        "PHONE"
      ],
      [
        101,
        123,
        "SKILL"
      ],
      [
        125,
        131,
        "SKILL"
      ],
      [
        133,
        152,
        "SKILL"
      ],
      [
        154,
        161,
        "SKILL"
      ]
    ]
  },
  {
    "entities": [
      [
        0,
        10,
        "PERSON"
      ],
      [
        11,
        32,
        "JOB"
      ],
      [
        33,
        51,
        "ADDRESS"
      ],
      [
        52,
        71,
        "EMAIL"
      ],
      [
        72,
        86,
        "PHONE"
      ],
      [
        101,
        109,
        "SKILL"
      ],
      [
        111,
        117,
        "SKILL"
      ],
      [
        119,
        135,
        "SKILL"
      ],
      [
        137,
        156,
        "SKILL"
      ]
    ]
  },
  {
    "entities": [
      [
        0,
        10,
        "PERSON"
      ],
      [
        11,
        33,
        "JOB"
      ],
      [
        34,
        57,
        "ADDRESS"
      ],
      [
        58,
        77,
        "EMAIL"
      ],
      [
        78,
        92,
        "PHONE"
      ],
      [
        107,
        113,
        "SKILL"
      ],
      [
        115,
        131,
        "SKILL"
      ],
      [
        133,
        139,
        "SKILL"
      ],
      [
        141,
        146,
        "SKILL"
      ]
    ]
  },
  {
    "entities": [
      [
        0,
        12,
        "PERSON"
      ],
      [
        13,
        35,
        "JOB"
      ],
      [
        36,
        55,
        "ADDRESS"
      ],
      [
        56,
        80,
        "EMAIL"
      ],
      [
        81,
        95,
        "PHONE"
      ],
      [
        110,
        126,
        "SKILL"
      ],
      [
        128,
        144,
        "SKILL"
      ],
      [
        146,
        151,
        "SKILL"
      ],
      [
        153,
        159,
        "SKILL"
      ]
    ]
  },
  {
    "entities": [
      [
        0,
        10,
        "PERSON"
      ],
      [
        11,
        30,
        "JOB"
      ],
      [
        31,
        54,
        "ADDRESS"
      ],
      [
        55,
        75,
        "EMAIL"
      ],
      [
        76,
        90,
        "PHONE"
      ],
      [
        105,
        111,
        "SKILL"
      ],
      [
        113,
        118,
        "SKILL"
      ],
      [
        120,
        126,
        "SKILL"
      ],
      [
        128,
        144,
        "SKILL"
      ]
    ]
  },
  {
    "entities": [
      [
        0,
        10,
        "PERSON"
      ],
      [
        11,
        30,
        "JOB"
      ],
      [
        31,
        53,
        "ADDRESS"
      ],
      [
        54,
        73,
        "EMAIL"
      ],
      [
        74,
        88,
        "PHONE"
      ],
      [
        103,
        108,
        "SKILL"
      ],
      [
        110,
        117,
        "SKILL"
      ],
      [
        119,
        135,
        "SKILL"
      ],
      [
        137,
        152,
        "SKILL"
      ]
    ]
  },
  {
    "entities": [
      [
        0,
        10,
        "PERSON"
      ],
      [
        11,
        31,
        "JOB"
      ],
      [
        32,
        50,
        "ADDRESS"
      ],
      [
        51,
        75,
        "EMAIL"
      ],
      [
        76,
        90,
        "PHONE"
      ],
      [
        105,
        111,
        "SKILL"
      ],
      [
        113,
        131,
        "SKILL"
      ],
      [
        133,
        143,
        "SKILL"
      ],
      [
        145,
        151,
        "SKILL"
      ]
    ]
  },
  {
    "entities": [
      [
        0,
        11,
        "PERSON"
      ],
      [
        12,
        21,
        "JOB"
      ],
      [
        22,
        45,
        "ADDRESS"
      ],
      [
        46,
        65,
        "EMAIL"
      ],
      [
        66,
        80,
        "PHONE"
      ],
      [
        95,
        111,
        "SKILL"
      ],
      [
        113,
        121,
        "SKILL"
      ],
      [
        123,
        129,
        "SKILL"
      ],
      [
        131,
        138,
        "SKILL"
      ]
    ]
  },
  {
    "entities": [
      [
        0,
        13,
        "PERSON"
      ],
      [
        14,
        26,
        "JOB"
      ],
      [
        27,
        50,
        "ADDRESS"
      ],
      [
        51,
        70,
        "EMAIL"
      ],
      [
        71,
        85,
        "PHONE"
      ],
      [
        100,
        106,
        "SKILL"
      ],
      [
        108,
        130,
        "SKILL"
      ],
      [
        132,
        148,
        "SKILL"
      ],
      [
        150,
        169,
        "SKILL"
      ]
    ]
  },
  {
    "entities": [
      [
        0,
        10,
        "PERSON"
      ],
      [
        11,
        27,
        "JOB"
      ],
      [
        28,
        46,
        "ADDRESS"
      ],
      [
        47,
        71,
        "EMAIL"
      ],
      [
        72,
        86,
        "PHONE"
      ],
      [
        101,
        107,
        "SKILL"
      ],
      [
        109,
        131,
        "SKILL"
      ],
      [
        133,
        148,
        "SKILL"
      ],
      [
        150,
        166,
        "SKILL"
      ]
    ]
  },
  {
    "entities": [
      [
        0,
        10,
        "PERSON"
      ],
      [
        11,
        23,
        "JOB"
      ],
      [
        24,
        47,
        "ADDRESS"
      ],
      [
        48,
        66,
        "EMAIL"
      ],
      [
        67,
        81,
        "PHONE"
      ],
      [
        96,
        106,
        "SKILL"
      ],
      [
        108,
        116,
        "SKILL"
      ],
      [
        118,
        123,
        "SKILL"
      ],
      [
        125,
        142,
        "SKILL"
      ]
    ]
  },
  {
    "entities": [
      [
        0,
        12,
        "PERSON"
      ],
      [
        13,
        29,
        "JOB"
      ],
      [
        30,
        52,
        "ADDRESS"
      ],
      [
        53,
        77,
        "EMAIL"
      ],
      [
        78,
        92,
        "PHONE"
      ],
      [
        107,
        122,
        "SKILL"
      ],
      [
        124,
        129,
        "SKILL"
      ],
      [
        131,
        137,
        "SKILL"
      ],
      [
        139,
        155,
        "SKILL"
      ]
    ]
  },
  {
    "entities": [
      [
        0,
        10,
        "PERSON"
      ],
      [
        11,
        31,
        "JOB"
      ],
      [
        32,
        55,
        "ADDRESS"
      ],
      [
        56,
        75,
        "EMAIL"
      ],
      [
        76,
        90,
        "PHONE"
      ],
      [
        105,
        110,
        "SKILL"
      ],
      [
        112,
        120,
        "SKILL"
      ],
      [
        122,
        144,
        "SKILL"
      ],
      [
        146,
        163,
        "SKILL"
      ]
    ]
  },
  {
    "entities": [
      [
        0,
        12,
        "PERSON"
      ],
      [
        13,
        22,
        "JOB"
      ],
      [
        23,
        42,
        "ADDRESS"
      ],
      [
        43,
        62,
        "EMAIL"
      ],
      [
        63,
        77,
        "PHONE"
      ],
      [
        92,
        110,
        "SKILL"
      ],
      [
        112,
        117,
        "SKILL"
      ],
      [
        119,
        127,
        "SKILL"
      ],
      [
        129,
        146,
        "SKILL"
      ]
    ]
  },
  {
    "entities": [
      [
        0,
        13,
        "PERSON"
      ],
      [
        14,
        33,
        "JOB"
      ],
      [
        34,
        56,
        "ADDRESS"
      ],
      [
        57,
        76,
        "EMAIL"
      ],
      [
        77,
        91,
        "PHONE"
      ],
      [
        106,
        122,
        "SKILL"
      ],
      [
        124,
        142,
        "SKILL"
      ],
      [
        144,
        160,
        "SKILL"
      ],
      [
        162,
        167,
        "SKILL"
      ]
    ]
  },
  {
    "entities": [
      [
        0,
        13,
        "PERSON"
      ],
      [
        14,
        33,
        "JOB"
      ],
      [
        34,
        57,
        "ADDRESS"
      ],
      [
        58,
        77,
        "EMAIL"
      ],
      [
        78,
        92,
        "PHONE"
      ],
      [
        107,
        114,
        "SKILL"
      ],
      [
        116,
        138,
        "SKILL"
      ],
      [
        140,
        156,
        "SKILL"
      ],
      [
        158,
        166,
        "SKILL"
      ]
    ]
  },
  {
    "entities": [
      [
        0,
        10,
        "PERSON"
      ],
      [
        11,
        30,
        "JOB"
      ],
      [
        31,
        49,
        "ADDRESS"
      ],
      [
        50,
        69,
        "EMAIL"
      ],
      [
        70,
        84,
        "PHONE"
      ],
      [
        99,
        116,
        "SKILL"
      ],
      [
        118,
        123,
        "SKILL"
      ],
      [
        125,
        131,
        "SKILL"
      ],
      [
        133,
        152,
        "SKILL"
      ]
    ]
  },
  {
    "entities": [
      [
        0,
        12,
        "PERSON"
      ],
      [
        13,
        32,
        "JOB"
      ],
      [
        33,
        55,
        "ADDRESS"
      ],
      [
        56,
        75,
        "EMAIL"
      ],
      [
        76,
        90,
        "PHONE"
      ],
      [
        105,
        122,
        "SKILL"
      ],
      [
        124,
        140,
        "SKILL"
      ],
      [
        142,
        149,
        "SKILL"
      ],
      [
        151,
        157,
        "SKILL"
      ]
    ]
  },
  {
    "entities": [
      [
        0,
        11,
        "PERSON"
      ],
      [
        12,
        34,
        "JOB"
      ],
      [
        35,
        58,
        "ADDRESS"
      ],
      [
        59,
        78,
        "EMAIL"
      ],
      [
        79,
        93,
        "PHONE"
      ],
      [
        108,
        123,
        "SKILL"
      ],
      [
        125,
        130,
        "SKILL"
      ],
      [
        132,
        148,
        "SKILL"
      ],
      [
        150,
        167,
        "SKILL"
      ]
    ]
  },
  {
    "entities": [
      [
        0,
        10,
        "PERSON"
      ],
      [
        11,
        31,
        "JOB"
      ],
      [
        32,
        51,
        "ADDRESS"
      ],
      [
        52,
        72,
        "EMAIL"
      ],
      [
        73,
        87,
        "PHONE"
      ],
      [
        102,
        105,
        "SKILL"
      ],
      [
        107,
        112,
        "SKILL"
      ],
      [
        114,
        129,
        "SKILL"
      ],
      [
        131,
        148,
        "SKILL"
      ]
    ]
  },
  {
    "entities": [
      [
        0,
        10,
        "PERSON"
      ],
      [
        11,
        30,
        "JOB"
      ],
      [
        31,
        49,
        "ADDRESS"
      ],
      [
        50,
        68,
        "EMAIL"
      ],
      [
        69,
        83,
        "PHONE"
      ],
      [
        98,
        105,
        "SKILL"
      ],
      [
        107,
        117,
        "SKILL"
      ],
      [
        119,
        124,
        "SKILL"
      ],
      [
        126,
        142,
        "SKILL"
      ]
    ]
  },
  {
    "entities": [
      [
        0,
        11,
        "PERSON"
      ],
      [
        12,
        31,
        "JOB"
      ],
      [
        32,
        54,
        "ADDRESS"
      ],
      [
        55,
        73,
        "EMAIL"
      ],
      [
        74,
        88,
        "PHONE"
      ],
      [
        103,
        120,
        "SKILL"
      ],
      [
        122,
        125,
        "SKILL"
      ],
      [
        127,
        137,
        "SKILL"
      ],
      [
        139,
        155,
        "SKILL"
      ]
    ]
  },
  {
    "entities": [
      [
        0,
        11,
        "PERSON"
      ],
      [
        12,
        28,
        "JOB"
      ],
      [
        29,
        52,
        "ADDRESS"
      ],
      [
        53,
        72,
        "EMAIL"
      ],
      [
        73,
        87,
        "PHONE"
      ],
      [
        102,
        105,
        "SKILL"
      ],
      [
        107,
        113,
        "SKILL"
      ],
      [
        115,
        133,
        "SKILL"
      ],
      [
        135,
        151,
        "SKILL"
      ]
    ]
  },
  {
    "entities": [
      [
        0,
        11,
        "PERSON"
      ],
      [
        12,
        31,
        "JOB"
      ],
      [
        32,
        51,
        "ADDRESS"
      ],
      [
        52,
        76,
        "EMAIL"
      ],
      [
        77,
        91,
        "PHONE"
      ],
      [
        106,
        123,
        "SKILL"
      ],
      [
        125,
        147,
        "SKILL"
      ],
      [
        149,
        165,
        "SKILL"
      ],
      [
        167,
        183,
        "SKILL"
      ]
    ]
  },
  {
    "entities": [
      [
        0,
        12,
        "PERSON"
      ],
      [
        13,
        29,
        "JOB"
      ],
      [
        30,
        53,
        "ADDRESS"
      ],
      [
        54,
        73,
        "EMAIL"
      ],
      [
        74,
        88,
        "PHONE"
      ],
      [
        103,
        109,
        "SKILL"
      ],
      [
        111,
        119,
        "SKILL"
      ],
      [
        121,
        124,
        "SKILL"
      ],
      [
        126,
        129,
        "SKILL"
      ]
    ]
  },
  {
    "entities": [
      [
        0,
        12,
        "PERSON"
      ],
      [
        13,
        32,
        "JOB"
      ],
      [
        33,
        51,
        "ADDRESS"
      ],
      [
        52,
        72,
        "EMAIL"
      ],
      [
        73,
        87,
        "PHONE"
      ],
      [
        102,
        109,
        "SKILL"
      ],
      [
        111,
        119,
        "SKILL"
      ],
      [
        121,
        124,
        "SKILL"
      ],
      [
        126,
        132,
        "SKILL"
      ]
    ]
  },
  {
    "entities": [
      [
        0,
        12,
        "PERSON"
      ],
      [
        13,
        32,
        "JOB"
      ],
      [
        33,
        51,
        "ADDRESS"
      ],
      [
        52,
        71,
        "EMAIL"
      ],
      [
        72,
        86,
        "PHONE"
      ],
      [
        101,
        120,
        "SKILL"
      ],
      [
        122,
        138,
        "SKILL"
      ],
      [
        140,
        150,
        "SKILL"
      ],
      [
        152,
        170,
        "SKILL"
      ]
    ]
  },
  {
    "entities": [
      [
        0,
        13,
        "PERSON"
      ],
      [
        14,
        35,
        "JOB"
      ],
      [
        36,
        59,
        "ADDRESS"
      ],
      [
        60,
        79,
        "EMAIL"
      ],
      [
        80,
        94,
        "PHONE"
      ],
      [
        109,
        115,
        "SKILL"
      ],
      [
        117,
        123,
        "SKILL"
      ],
      [
        125,
        142,
        "SKILL"
      ],
      [
        144,
        160,
        "SKILL"
      ]
    ]
  },
  {
    "entities": [
      [
        0,
        12,
        "PERSON"
      ],
      [
        13,
        32,
        "JOB"
      ],
      [
        33,
        56,
        "ADDRESS"
      ],
      [
        57,
        77,
        "EMAIL"
      ],
      [
        78,
        92,
        "PHONE"
      ],
      [
        107,
        125,
        "SKILL"
      ],
      [
        127,
        134,
        "SKILL"
      ],
      [
        136,
        139,
        "SKILL"
      ],
      [
        141,
        157,
        "SKILL"
      ]
    ]
  }
]